coast_sim-0.1.2.dist-info/licenses/LICENSE
conops/__init__.py
conops/_version.py
conops/common/__init__.py
conops/common/common.py
conops/common/enums.py
conops/common/vector.py
conops/config/__init__.py
conops/config/acs.py
conops/config/battery.py
conops/config/communications.py
conops/config/config.py
conops/config/constants.py
conops/config/constraint.py
conops/config/data_generator.py
conops/config/fault_management.py
conops/config/groundstation.py
conops/config/instrument.py
conops/config/observation_categories.py
conops/config/power.py
conops/config/recorder.py
conops/config/solar_panel.py
conops/config/spacecraft_bus.py
conops/config/thermal.py
conops/config/visualization.py
conops/ditl/__init__.py
conops/ditl/ditl.py
conops/ditl/ditl_event.py
conops/ditl/ditl_log.py
conops/ditl/ditl_log_store.py
conops/ditl/ditl_mixin.py
conops/ditl/ditl_stats.py
conops/ditl/queue_ditl.py
conops/schedulers/__init__.py
conops/schedulers/queue_scheduler.py
conops/schedulers/scheduler.py
conops/simulation/__init__.py
conops/simulation/acs.py
conops/simulation/acs_command.py
conops/simulation/emergency_charging.py
conops/simulation/passes.py
conops/simulation/roll.py
conops/simulation/saa.py
conops/simulation/slew.py
conops/targets/__init__.py
conops/targets/plan.py
conops/targets/plan_entry.py
conops/targets/pointing.py
conops/targets/target_queue.py
conops/visualization/__init__.py
conops/visualization/acs_mode_analysis.py
conops/visualization/data_management.py
conops/visualization/ditl_telemetry.py
conops/visualization/ditl_timeline.py
conops/visualization/sky_pointing.py
docs/Makefile
docs/README.md
docs/communications.rst
docs/conf.py
docs/configuration.rst
docs/contributing.rst
docs/data_management.rst
docs/examples.rst
docs/fault_management.rst
docs/index.rst
docs/installation.rst
docs/make.bat
docs/quickstart.rst
docs/requirements.txt
docs/sky_pointing_visualization.rst
docs/target_of_opportunity.rst
docs/visualization.rst
docs/_static/coast-sim-logo.png
docs/api/conops.battery.rst
coast_sim-0.1.2.dist-info/METADATA
coast_sim-0.1.2.dist-info/WHEEL
coast_sim-0.1.2.dist-info/top_level.txt
coast_sim-0.1.2.dist-info/RECORD
