Metadata-Version: 2.4
Name: coast-sim
Version: 0.1.2
Summary: COASTSim: ConOps Astronomical Space Telescope Simulator
Author-email: "Jamie A. Kennea" <jamie@cosmicfrontier.org>
Maintainer-email: "Jamie A. Kennea" <jamie@cosmicfrontier.org>
License-Expression: Apache-2.0
Project-URL: Documentation, https://coastsim.readthedocs.io/en/latest/
Project-URL: Homepage, https://github.com/CosmicFrontierLabs/coast-sim/
Project-URL: Source, https://github.com/CosmicFrontierLabs/coast-sim/
Project-URL: Changelog, https://github.com/CosmicFrontierLabs/coast-sim/blob/main/CHANGELOG.md
Classifier: Development Status :: 5 - Production/Stable
Classifier: Intended Audience :: Science/Research
Classifier: Programming Language :: Python :: 3
Classifier: Programming Language :: Python :: 3.10
Classifier: Programming Language :: Python :: 3.11
Classifier: Programming Language :: Python :: 3.12
Classifier: Programming Language :: Python :: 3.13
Classifier: Programming Language :: Python :: 3.14
Classifier: Programming Language :: Python :: 3 :: Only
Requires-Python: >=3.10
License-File: LICENSE
Requires-Dist: astropy>=6
Requires-Dist: matplotlib>=3.10
Requires-Dist: numpy>=2
Requires-Dist: pydantic>=2.12
Requires-Dist: pyproj>=3.7.0
Requires-Dist: pytz>=2025.2
Requires-Dist: rust-ephem>=0.1.12
Requires-Dist: shapely>=2
Requires-Dist: tqdm>=4.67
Provides-Extra: jupyter
Requires-Dist: ipympl>=0.9.7; extra == "jupyter"
Requires-Dist: jupyter>=1.1.1; extra == "jupyter"
Requires-Dist: ipywidgets>=8.0; extra == "jupyter"
Provides-Extra: dev
Requires-Dist: mypy>=1.15; extra == "dev"
Requires-Dist: pre-commit>=4.2; extra == "dev"
Requires-Dist: ruff>=0.11; extra == "dev"
Requires-Dist: types-pytz>=2025.2.0.20250326; extra == "dev"
Requires-Dist: types-shapely>=2.1.0.20250418; extra == "dev"
Requires-Dist: types-tqdm>=4.67.0.20250809; extra == "dev"
Provides-Extra: test
Requires-Dist: pytest>=8; extra == "test"
Requires-Dist: pytest-cov>=7; extra == "test"
Provides-Extra: docs
Requires-Dist: sphinx>=7.0; extra == "docs"
Requires-Dist: sphinx-rtd-theme>=2.0; extra == "docs"
Requires-Dist: myst-parser>=2.0; extra == "docs"
Requires-Dist: sphinx-autodoc-typehints>=1.24; extra == "docs"
Dynamic: license-file
